nk_model_assist/__init__.py
nk_model_assist/data_checker.py
nk_model_assist/data_loader.py
nk_model_assist/modelling.py
nk_model_assist/preprocess.py
nk_model_assist-0.1.3.dist-info/LICENSE
nk_model_assist-0.1.3.dist-info/METADATA
nk_model_assist-0.1.3.dist-info/WHEEL
nk_model_assist-0.1.3.dist-info/top_level.txt
nk_model_assist-0.1.3.dist-info/RECORD
