Metadata-Version: 2.1
Name: nk-model-assist
Version: 0.1.3
Summary: This is a package to assist with model training and evaluation.
Home-page: https://github.com/yourusername/nk-modelling
Author: Nithesh Kumar
Author-email: nitheshmanimaran@example.com
Classifier: Programming Language :: Python :: 3
Classifier: License :: OSI Approved :: MIT License
Classifier: Operating System :: OS Independent
Requires-Python: >=3.6
License-File: LICENSE
Requires-Dist: pandas
Requires-Dist: numpy
